cmod/__init__.py
cmod/_cmod.cpython-38-darwin.so
cmod/pymod.py
hello_c_extension-0.5.dist-info/LICENSE
hello_c_extension-0.5.dist-info/METADATA
hello_c_extension-0.5.dist-info/WHEEL
hello_c_extension-0.5.dist-info/top_level.txt
hello_c_extension-0.5.dist-info/RECORD
